minidevice/DroidCast.py
minidevice/QueueUtils.py
minidevice/__init__.py
minidevice/adbcap.py
minidevice/adbtouch.py
minidevice/config.py
minidevice/device.py
minidevice/logger.py
minidevice/maatouch.py
minidevice/minicap.py
minidevice/minitouch.py
minidevice/screencap.py
minidevice/touch.py
minidevice/utils.py
minidevice/bin/DroidCast-debug-1.2.0.apk
minidevice/bin/maatouch
minidevice/bin/minicap/jni/android-10/armeabi-v7a/minicap.so
minidevice/bin/minicap/jni/android-14/armeabi-v7a/minicap.so
minidevice/bin/minicap/jni/android-14/x86/minicap.so
minidevice/bin/minicap/jni/android-15/armeabi-v7a/minicap.so
minidevice/bin/minicap/jni/android-15/x86/minicap.so
minidevice/bin/minicap/jni/android-16/armeabi-v7a/minicap.so
minidevice/bin/minicap/jni/android-16/x86/minicap.so
minidevice/bin/minicap/jni/android-17/armeabi-v7a/minicap.so
minidevice/bin/minicap/jni/android-17/x86/minicap.so
minidevice/bin/minicap/jni/android-18/armeabi-v7a/minicap.so
minidevice/bin/minicap/jni/android-18/x86/minicap.so
minidevice/bin/minicap/jni/android-19/armeabi-v7a/minicap.so
minidevice/bin/minicap/jni/android-19/x86/minicap.so
minidevice/bin/minicap/jni/android-21/arm64-v8a/minicap.so
minidevice/bin/minicap/jni/android-21/armeabi-v7a/minicap.so
minidevice/bin/minicap/jni/android-21/x86/minicap.so
minidevice/bin/minicap/jni/android-21/x86_64/minicap.so
minidevice/bin/minicap/jni/android-22/arm64-v8a/minicap.so
minidevice/bin/minicap/jni/android-22/armeabi-v7a/minicap.so
minidevice/bin/minicap/jni/android-22/x86/minicap.so
minidevice/bin/minicap/jni/android-22/x86_64/minicap.so
minidevice/bin/minicap/jni/android-23/arm64-v8a/minicap.so
minidevice/bin/minicap/jni/android-23/armeabi-v7a/minicap.so
minidevice/bin/minicap/jni/android-23/x86/minicap.so
minidevice/bin/minicap/jni/android-23/x86_64/minicap.so
minidevice/bin/minicap/jni/android-24/arm64-v8a/minicap.so
minidevice/bin/minicap/jni/android-24/armeabi-v7a/minicap.so
minidevice/bin/minicap/jni/android-24/x86/minicap.so
minidevice-3.0.1.dist-info/METADATA
minidevice-3.0.1.dist-info/WHEEL
minidevice-3.0.1.dist-info/top_level.txt
minidevice-3.0.1.dist-info/RECORD
