Metadata-Version: 2.1
Name: minidevice
Version: 3.0.1
Summary: Android Auto Pypi
Home-page: https://github.com/NakanoSanku/minidevice
Author: KateTseng
Author-email: Kate.TsengK@outlook.com
License: MIT
Keywords: Android
Requires-Python: >=3
Requires-Dist: adbutils
